django_mongodb/__init__.py
django_mongodb/base.py
django_mongodb/client.py
django_mongodb/compiler.py
django_mongodb/creation.py
django_mongodb/cursor.py
django_mongodb/database.py
django_mongodb/expressions.py
django_mongodb/features.py
django_mongodb/introspection.py
django_mongodb/managers.py
django_mongodb/models.py
django_mongodb/operations.py
django_mongodb/query.py
django_mongodb/schema.py
django_mongodb/utils.py
django_mongo_backend-0.29.dist-info/METADATA
django_mongo_backend-0.29.dist-info/WHEEL
django_mongo_backend-0.29.dist-info/RECORD
