Metadata-Version: 2.3
Name: django-mongo-backend
Version: 0.29
Summary: 
License: MIT
Keywords: django,mongodb,backend
Author: gersmann
Requires-Python: >=3.11,<4.0
Classifier: Development Status :: 3 - Alpha
Classifier: Environment :: Web Environment
Classifier: Framework :: Django
Classifier: Framework :: Django :: 5.0
Classifier: Framework :: Django :: 5.1
Classifier: Framework :: Django :: 5.2
Classifier: Intended Audience :: Developers
Classifier: License :: OSI Approved :: MIT License
Classifier: Operating System :: OS Independent
Classifier: Programming Language :: Python :: 3
Classifier: Programming Language :: Python :: 3.11
Classifier: Programming Language :: Python :: 3.12
Classifier: Programming Language :: Python :: 3.13
Provides-Extra: django5
Provides-Extra: django51
Provides-Extra: django52
Requires-Dist: dictlib (>=1.1,<2.0)
Requires-Dist: pymongo (>=4.11,<5.0)
Project-URL: Homepage, https://github.com/parcellab/django-mongo-backend
Project-URL: Repository, https://github.com/parcellab/django-mongo-backend
